[
  {
    "caller_name": "Farah",
    "caller_phone_no": "8765432109",
    "description": "Internet is slow and disconnects frequently.",
    "location": "Kanpur",
    "date_time": "2025-06-08T15:00:00"
  },
  {
    "caller_name": "Eshan",
    "caller_phone_no": "6543210987",
    "description": "System running slow, taking minutes to boot.",
    "location": "Noida",
    "date_time": "2025-06-08T22:00:00"
  },
  {
    "caller_name": "Harshita",
    "caller_phone_no": "5432109876",
    "description": "There is a complete power outage in the building since last night.",
    "location": "Noida",
    "date_time": "2025-06-05T11:00:00"
  },
  {
    "caller_name": "Bhavna",
    "caller_phone_no": "2109876543",
    "description": "There is a complete power outage in the building since last night.",
    "location": "Ghaziabad",
    "date_time": "2025-06-07T04:00:00"
  },
  {
    "caller_name": "Chirag",
    "caller_phone_no": "3210987654",
    "description": "Building lost all power. Lights and fans not functioning.",
    "location": "Agra",
    "date_time": "2025-06-05T22:00:00"
  },
  {
    "caller_name": "Eshan",
    "caller_phone_no": "9876543210",
    "description": "Internet is slow and disconnects frequently.",
    "location": "Ghaziabad",
    "date_time": "2025-06-09T00:00:00"
  },
  {
    "caller_name": "Aarav",
    "caller_phone_no": "2109876543",
    "description": "Internet connection drops every 10 minutes, very unstable.",
    "location": "Ghaziabad",
    "date_time": "2025-06-05T16:00:00"
  },
  {
    "caller_name": "Gopal",
    "caller_phone_no": "9876543210",
    "description": "Internet connection drops every 10 minutes, very unstable.",
    "location": "Varanasi",
    "date_time": "2025-06-07T13:00:00"
  },
  {
    "caller_name": "Farah",
    "caller_phone_no": "5432109876",
    "description": "The printer won't print anything, jobs stuck in queue.",
    "location": "Ghaziabad",
    "date_time": "2025-06-08T22:00:00"
  },
  {
    "caller_name": "Gopal",
    "caller_phone_no": "9876543210",
    "description": "Internet is slow and disconnects frequently.",
    "location": "Noida",
    "date_time": "2025-06-05T14:00:00"
  },
  {
    "caller_name": "Aarav",
    "caller_phone_no": "4321098765",
    "description": "The printer won't print anything, jobs stuck in queue.",
    "location": "Varanasi",
    "date_time": "2025-06-06T09:00:00"
  },
  {
    "caller_name": "Aarav",
    "caller_phone_no": "6543210987",
    "description": "The printer won't print anything, jobs stuck in queue.",
    "location": "Lucknow",
    "date_time": "2025-06-08T00:00:00"
  },
  {
    "caller_name": "Harshita",
    "caller_phone_no": "5432109876",
    "description": "Computer performance degraded significantly over the past day.",
    "location": "Bareilly",
    "date_time": "2025-06-08T00:00:00"
  },
  {
    "caller_name": "Gopal",
    "caller_phone_no": "3210987654",
    "description": "The printer won't print anything, jobs stuck in queue.",
    "location": "Meerut",
    "date_time": "2025-06-06T15:00:00"
  },
  {
    "caller_name": "Aarav",
    "caller_phone_no": "2109876543",
    "description": "Internet connection drops every 10 minutes, very unstable.",
    "location": "Meerut",
    "date_time": "2025-06-06T18:00:00"
  },
  {
    "caller_name": "Bhavna",
    "caller_phone_no": "2109876543",
    "description": "Printer in the admin office is not responding.",
    "location": "Ghaziabad",
    "date_time": "2025-06-08T18:00:00"
  },
  {
    "caller_name": "Aarav",
    "caller_phone_no": "6543210987",
    "description": "Internet connection drops every 10 minutes, very unstable.",
    "location": "Kanpur",
    "date_time": "2025-06-08T21:00:00"
  },
  {
    "caller_name": "Bhavna",
    "caller_phone_no": "6543210987",
    "description": "System running slow, taking minutes to boot.",
    "location": "Agra",
    "date_time": "2025-06-08T07:00:00"
  },
  {
    "caller_name": "Gopal",
    "caller_phone_no": "8765432109",
    "description": "Internet connection drops every 10 minutes, very unstable.",
    "location": "Kanpur",
    "date_time": "2025-06-05T12:00:00"
  },
  {
    "caller_name": "Gopal",
    "caller_phone_no": "4321098765",
    "description": "Internet is slow and disconnects frequently.",
    "location": "Kanpur",
    "date_time": "2025-06-08T23:00:00"
  }
]